setup.py
ze/__init__.py
ze/settings.py
ze/extensions/__init__.py
ze/extensions/google.py
ze/items/__init__.py
ze/items/creativework.py
ze/pipelines/__init__.py
ze/processors/__init__.py
ze/processors/article.py
ze/processors/common.py
ze/processors/html.py
ze/spiders/__init__.py
ze/spiders/cartacapital.py
ze/spiders/estadao.py
ze/spiders/folhadesp.py
ze/spiders/g1.py
ze/spiders/ig.py
ze/spiders/uol.py
ze/spiders/veja.py
ze/utils/__init__.py
ze/utils/file.py
ze_the_scraper.egg-info/PKG-INFO
ze_the_scraper.egg-info/SOURCES.txt
ze_the_scraper.egg-info/dependency_links.txt
ze_the_scraper.egg-info/entry_points.txt
ze_the_scraper.egg-info/top_level.txt