Metadata-Version: 1.1
Name: ze-the-scraper
Version: 0.0.17.dev1
Summary: Scaper to lager portal of news in Brazil.
Home-page: http://github.com/labic/ze-the-scraper
Author: @gustavorps, @ligiaiv
Author-email: email+labic.net@gustavorps.net, ligiaiv@gmail.com
License: MIT
Keywords: scrapy scraper spider crawler brazil news estadao veja folha-de-sp
Platform: UNKNOWN
Classifier: Development Status :: 3 - Alpha
Classifier: Intended Audience :: Developers
Classifier: Intended Audience :: Information Technology
Classifier: Intended Audience :: Science/Research
Classifier: License :: OSI Approved :: Academic Free License (AFL)
Classifier: Programming Language :: Python :: 3.4
Classifier: Operating System :: OS Independent
Classifier: Topic :: Internet :: WWW/HTTP :: Indexing/Search
